oteapi_dlite/__init__.py
oteapi_dlite/models.py
oteapi_dlite/entities/Image.json
oteapi_dlite/strategies/__init__.py
oteapi_dlite/strategies/convert.py
oteapi_dlite/strategies/filter.py
oteapi_dlite/strategies/generate.py
oteapi_dlite/strategies/mapping.py
oteapi_dlite/strategies/parse.py
oteapi_dlite/strategies/parse_excel.py
oteapi_dlite/strategies/parse_image.py
oteapi_dlite/strategies/serialise.py
oteapi_dlite/strategies/settings.py
oteapi_dlite/utils/__init__.py
oteapi_dlite/utils/exceptions.py
oteapi_dlite/utils/nputils.py
oteapi_dlite/utils/utils.py
oteapi_dlite-1.0.0.dist-info/entry_points.txt
oteapi_dlite-1.0.0.dist-info/licenses/LICENSE
oteapi_dlite-1.0.0.dist-info/WHEEL
oteapi_dlite-1.0.0.dist-info/METADATA
oteapi_dlite-1.0.0.dist-info/RECORD
