Metadata-Version: 2.4
Name: oteapi-dlite
Version: 1.0.0
Summary: DLite plugin for Open Translation Environment (OTE) API.
Keywords: OTE,OTEAPI,LITE,OTEAPI-DLITE
Author-email: SINTEF <Team4.0@SINTEF.no>
Requires-Python: ~=3.10
Classifier: Programming Language :: Python :: 3
Classifier: Programming Language :: Python :: 3.10
Classifier: Programming Language :: Python :: 3.11
Classifier: Programming Language :: Python :: 3.12
Classifier: License :: OSI Approved :: MIT License
License-File: LICENSE
Requires-Dist: DLite-Python>=0.5.29,<1
Requires-Dist: numpy>=2.1,<3
Requires-Dist: oteapi-core>=1.0,<2
Requires-Dist: pydantic-settings>=2.8,<3
Requires-Dist: Pillow>=9.0.1,<12
Requires-Dist: tripper[mappings]>=0.4.0,<1
Requires-Dist: oteapi-dlite[docs, testing] ; extra == "dev"
Requires-Dist: pre-commit==4.2.0 ; extra == "dev"
Requires-Dist: mike~=2.1 ; extra == "docs"
Requires-Dist: mkdocs~=1.6 ; extra == "docs"
Requires-Dist: mkdocs-autorefs~=1.4 ; extra == "docs"
Requires-Dist: mkdocs-awesome-pages-plugin~=2.10 ; extra == "docs"
Requires-Dist: mkdocs-material~=9.6 ; extra == "docs"
Requires-Dist: mkdocstrings[python]~=0.29.1 ; extra == "docs"
Requires-Dist: PyYAML~=6.0 ; extra == "testing"
Requires-Dist: otelib~=1.0 ; extra == "testing"
Requires-Dist: rdflib>=5.0.0,<8 ; extra == "testing"
Requires-Dist: pytest==8.3.5 ; extra == "testing"
Requires-Dist: pytest-cov==6.1.1 ; extra == "testing"
Project-URL: Changelog, https://github.com/EMMC-ASBL/oteapi-dlite/blob/master/CHANGELOG.md
Project-URL: Documentation, https://EMMC-ASBL.github.io/oteapi-dlite
Project-URL: Home, https://github.com/EMMC-ASBL/oteapi-dlite
Project-URL: Issue Tracker, https://github.com/EMMC-ASBL/oteapi-dlite/issues
Project-URL: Package, https://pypi.org/project/oteapi-dlite
Project-URL: Source, https://github.com/EMMC-ASBL/oteapi-dlite
Provides-Extra: dev
Provides-Extra: docs
Provides-Extra: testing
